{
  "data": {
    "title": "The Sunday Currently, Volume 24",
    "date": "2014-05-04",
    "categories": [
      "the-sunday-currently"
    ],
    "tags": [
      "the-everyday",
      "travel-planning",
      "weekend"
    ],
    "id": "1601",
    "slug": "the-sunday-currently-volume-24"
  },
  "content": {
    "type": "doc",
    "content": [
      {
        "type": "paragraph",
        "content": [
          {
            "type": "text",
            "text": "[caption id=\"\" align=\"aligncenter\" width=\"480\"]"
          },
          {
            "type": "image",
            "attrs": {
              "src": "images/20140504-121011.jpg",
              "alt": "20140504-121011.jpg",
              "title": null
            }
          },
          {
            "type": "text",
            "text": " Happy Sunday from Banana and me![/caption]"
          }
        ]
      },
      {
        "type": "paragraph",
        "content": [
          {
            "type": "text",
            "text": "This weekend has been all about getting ready for our trip this Wednesday!! I've been pre-writing blog posts, running tons of errands, making reservations at restaurants in Paris, spending time with friends, etc. It's been fun, and I am just so, so excited."
          }
        ]
      },
      {
        "type": "heading",
        "attrs": {
          "level": 2
        },
        "content": [
          {
            "type": "text",
            "marks": [
              {
                "type": "em"
              },
              {
                "type": "strong"
              }
            ],
            "text": "Currently..."
          }
        ]
      },
      {
        "type": "paragraph",
        "content": [
          {
            "type": "text",
            "marks": [
              {
                "type": "em"
              }
            ],
            "text": "Reading"
          },
          {
            "type": "text",
            "text": "  "
          },
          {
            "type": "text",
            "marks": [
              {
                "type": "link",
                "attrs": {
                  "href": "http://www.amazon.com/Night-Film-Novel-Marisha-Pessl/dp/140006788X",
                  "title": null
                }
              }
            ],
            "text": "Night Film"
          },
          {
            "type": "text",
            "text": ". I was not very good about reading this week (which is sad considering I posted about doing a "
          },
          {
            "type": "text",
            "marks": [
              {
                "type": "link",
                "attrs": {
                  "href": "http://everydayaccountsblog.com/2014/05/01/semi-charmed-summer-2014-book-challenge/",
                  "title": "Semi-Charmed Summer 2014 Book Challenge"
                }
              }
            ],
            "text": "book challenge"
          },
          {
            "type": "text",
            "text": " last week). But I'm still loving it and am planning on wrapping it up on the plane next week."
          }
        ]
      },
      {
        "type": "paragraph",
        "content": [
          {
            "type": "text",
            "marks": [
              {
                "type": "em"
              }
            ],
            "text": "Writing"
          },
          {
            "type": "text",
            "text": "  so many blog posts!"
          }
        ]
      },
      {
        "type": "paragraph",
        "content": [
          {
            "type": "text",
            "marks": [
              {
                "type": "em"
              }
            ],
            "text": "Listening"
          },
          {
            "type": "text",
            "text": "  to a mix of stations on Pandora and my laundry going"
          }
        ]
      },
      {
        "type": "paragraph",
        "content": [
          {
            "type": "text",
            "marks": [
              {
                "type": "em"
              }
            ],
            "text": "Thinking"
          },
          {
            "type": "text",
            "text": "  about London and Paris.... I'm afraid I'm going to be quite repetitive in this post."
          }
        ]
      },
      {
        "type": "paragraph",
        "content": [
          {
            "type": "text",
            "marks": [
              {
                "type": "em"
              }
            ],
            "text": "Smelling"
          },
          {
            "type": "text",
            "text": "  the Bath and Body Works Cinnamon Sugared Donut candle. Normally, I save the dessert and baking scented candles for the fall and winter, but I could not turn this one down while browsing around BBW. It is delightful, and I feel like I'm eating a donut when I smell this candle."
          }
        ]
      },
      {
        "type": "paragraph",
        "content": [
          {
            "type": "text",
            "marks": [
              {
                "type": "em"
              }
            ],
            "text": "Wishing"
          },
          {
            "type": "text",
            "text": "  time would slow down today just a little bit. So much to do in so little time!"
          }
        ]
      },
      {
        "type": "paragraph",
        "content": [
          {
            "type": "text",
            "marks": [
              {
                "type": "em"
              }
            ],
            "text": "Hoping"
          },
          {
            "type": "text",
            "text": "  that things go smoothly at work Monday and Tuesday, so that I can leave the office for a week and a half feeling like I've left projects in a good place."
          }
        ]
      },
      {
        "type": "paragraph",
        "content": [
          {
            "type": "text",
            "marks": [
              {
                "type": "em"
              }
            ],
            "text": "Wearing"
          },
          {
            "type": "text",
            "text": "  my pjs. I need to run and change here very soon because we are having brunch with friends!"
          }
        ]
      },
      {
        "type": "paragraph",
        "content": [
          {
            "type": "text",
            "marks": [
              {
                "type": "em"
              }
            ],
            "text": "Loving"
          },
          {
            "type": "text",
            "text": "  oh, you know, all things London and Paris :)"
          }
        ]
      },
      {
        "type": "paragraph",
        "content": [
          {
            "type": "text",
            "marks": [
              {
                "type": "em"
              }
            ],
            "text": "Wanting"
          },
          {
            "type": "text",
            "text": "  brunch! We are going to a great place nearby, and I can't wait to try out something new along with my standard cup of coffee."
          }
        ]
      },
      {
        "type": "paragraph",
        "content": [
          {
            "type": "text",
            "marks": [
              {
                "type": "em"
              }
            ],
            "text": "Needing"
          },
          {
            "type": "text",
            "text": "  to do lots and lots and lots of things. My to-do list is massive, y'all."
          }
        ]
      },
      {
        "type": "paragraph",
        "content": [
          {
            "type": "text",
            "marks": [
              {
                "type": "em"
              }
            ],
            "text": "Feeling"
          },
          {
            "type": "text",
            "text": "  ... Can I say it again without being annoying? So excited for our trip!!!"
          }
        ]
      },
      {
        "type": "paragraph",
        "content": [
          {
            "type": "text",
            "marks": [
              {
                "type": "em"
              }
            ],
            "text": "Clicking"
          },
          {
            "type": "text",
            "text": "  blog posts, but I should stop and get ready for the day"
          },
          {
            "type": "image",
            "attrs": {
              "src": "https://twitter.com/siddathornton",
              "alt": null,
              "title": null
            }
          }
        ]
      },
      {
        "type": "paragraph",
        "content": [
          {
            "type": "text",
            "text": "Have a beautiful Sunday!"
          }
        ]
      },
      {
        "type": "paragraph",
        "content": [
          {
            "type": "text",
            "marks": [
              {
                "type": "em"
              }
            ],
            "text": "This post is for the blog link up on "
          },
          {
            "type": "text",
            "marks": [
              {
                "type": "em"
              },
              {
                "type": "link",
                "attrs": {
                  "href": "http://siddathornton.blogspot.com/",
                  "title": null
                }
              }
            ],
            "text": "siddathornton"
          },
          {
            "type": "text",
            "marks": [
              {
                "type": "em"
              }
            ],
            "text": ". Share yours and link it up!"
          }
        ]
      },
      {
        "type": "paragraph",
        "content": [
          {
            "type": "text",
            "text": "Click "
          },
          {
            "type": "text",
            "marks": [
              {
                "type": "link",
                "attrs": {
                  "href": "http://www.everydayaccountsblog.com/category/the-sunday-currently/",
                  "title": null
                }
              }
            ],
            "text": "here"
          },
          {
            "type": "text",
            "text": " to see all of my The Sunday Currently posts."
          }
        ]
      }
    ]
  }
}